{
  "easy": [
    {"id":"E1","title":"Maximum Number","question":"Find the maximum number in an array.","constraints":"Array length >= 1, integers","examples":[{"input":"[1,3,2,8,5]","output":"8"}]},
    {"id":"E2","title":"Minimum Number","question":"Find the minimum number in an array.","constraints":"Array length >= 1, integers","examples":[{"input":"[2,5,1,9]","output":"1"}]},
    {"id":"E3","title":"Check Sorted","question":"Return true if the array is sorted in non-decreasing order.","constraints":"Array of integers","examples":[{"input":"[1,2,2,3]","output":"true"}]},
    {"id":"E4","title":"Remove Duplicates From Sorted Array","question":"Remove duplicates in-place from a sorted array and return new length.","constraints":"Sorted array","examples":[{"input":"[1,1,2]","output":"2"}]},
    {"id":"E5","title":"Move Zeros To End","question":"Move all zeros in an array to the end while maintaining order of non-zero elements.","constraints":"In-place","examples":[{"input":"[0,1,0,3]","output":"[1,3,0,0]"}]},
    {"id":"E6","title":"Second Largest","question":"Find the second largest element in an array.","constraints":"Array length >= 2","examples":[{"input":"[4,2,1,5]","output":"4"}]},
    {"id":"E7","title":"Count Even Odd","question":"Count the number of even and odd numbers in an array.","constraints":"Integers","examples":[{"input":"[1,2,3,4]","output":"evens=2,odds=2"}]},
    {"id":"E8","title":"Reverse Array In-place","question":"Reverse an array in-place.","constraints":"O(1) extra space","examples":[{"input":"[1,2,3]","output":"[3,2,1]"}]},
    {"id":"E9","title":"Sum Of Elements","question":"Return the sum of all elements in the array.","constraints":"Integers","examples":[{"input":"[1,2,3]","output":"6"}]},
    {"id":"E10","title":"Linear Search","question":"Return the index of a target using linear search, or -1 if not found.","constraints":"Array of integers","examples":[{"input":"array=[1,2,3],target=2","output":"1"}]},
    {"id":"E11","title":"Single Element","question":"In an array where every element appears twice except one, find that single element.","constraints":"All integers","examples":[{"input":"[2,2,3]","output":"3"}]},
    {"id":"E12","title":"First Non-repeating","question":"Find the first non-repeating element in an array.","constraints":"Return index or value","examples":[{"input":"[2,3,2,4]","output":"3"}]},
    {"id":"E13","title":"Merge Two Sorted Arrays","question":"Merge two sorted arrays into a single sorted array.","constraints":"Output new array","examples":[{"input":"[1,3] and [2,4]","output":"[1,2,3,4]"}]},
    {"id":"E14","title":"Rotate Array By K","question":"Rotate array to the right by k steps.","constraints":"k >= 0","examples":[{"input":"[1,2,3,4],k=1","output":"[4,1,2,3]"}]},
    {"id":"E15","title":"Arrays Equal","question":"Check if two arrays contain the same elements (order ignored).","constraints":"Integers","examples":[{"input":"[1,2] and [2,1]","output":"true"}]},
    {"id":"E16","title":"Reverse String","question":"Reverse a string.","constraints":"In-place if possible","examples":[{"input":"\"abc\"","output":"\"cba\""}]},
    {"id":"E17","title":"String Palindrome","question":"Check if a string is a palindrome.","constraints":"Case-sensitive unless stated","examples":[{"input":"\"aba\"","output":"true"}]},
    {"id":"E18","title":"First Non-repeating Char","question":"Return the first non-repeating character in a string.","constraints":"Return char or -1 if none","examples":[{"input":"\"leetcode\"","output":"\"l\""}]},
    {"id":"E19","title":"Count Vowels Consonants","question":"Count vowels and consonants in a string.","constraints":"Alphabetic chars only","examples":[{"input":"\"hello\"","output":"vowels=2,consonants=3"}]},
    {"id":"E20","title":"Anagram Check","question":"Check if two strings are anagrams.","constraints":"Only lowercase unless stated","examples":[{"input":"\"rat\",\"tar\"","output":"true"}]},
    {"id":"E21","title":"Remove Vowels","question":"Remove vowels from a string and return result.","constraints":"English vowels","examples":[{"input":"\"hello\"","output":"\"hll\""}]},
    {"id":"E22","title":"Longest Common Prefix","question":"Find the longest common prefix string amongst an array of strings.","constraints":"Return \"\" if none","examples":[{"input":"[\"flower\",\"flow\",\"flight\"]","output":"\"fl\""}]},
    {"id":"E23","title":"To Upper Case Without Built-in","question":"Convert a string to uppercase without using built-ins.","constraints":"ASCII letters","examples":[{"input":"\"abc\"","output":"\"ABC\""}]},
    {"id":"E24","title":"Most Frequent Char","question":"Return the character with highest frequency in a string.","constraints":"Return one if tie","examples":[{"input":"\"aab\"","output":"\"a\""}]},
    {"id":"E25","title":"Digits Only","question":"Check if string contains only digits.","constraints":"Return boolean","examples":[{"input":"\"123\"","output":"true"}]},
    {"id":"E26","title":"Word Count","question":"Count number of words in a sentence separated by spaces.","constraints":"Trim spaces","examples":[{"input":"\"Hello world\"","output":"2"}]},
    {"id":"E27","title":"String Rotation Check","question":"Check if one string is rotation of another.","constraints":"Same length","examples":[{"input":"s1=\"abc\",s2=\"bca\"","output":"true"}]},
    {"id":"E28","title":"Replace Spaces","question":"Replace spaces in a string with \"%20\".","constraints":"URL-encoding style","examples":[{"input":"\"Mr John\"","output":"\"Mr%20John\""}]},
    {"id":"E29","title":"Remove Duplicate Chars","question":"Remove duplicate characters from string preserving order.","constraints":"ASCII chars","examples":[{"input":"\"aabb\"","output":"\"ab\""}]},
    {"id":"E30","title":"Substring Exists","question":"Check if substring exists in a string (naive method).","constraints":"Return boolean","examples":[{"input":"s=\"hello\",sub=\"ell\"","output":"true"}]},
    {"id":"E31","title":"Frequency Map Array","question":"Return frequency map of array elements.","constraints":"Integers","examples":[{"input":"[1,2,2]","output":"{1:1,2:2}"}]},
    {"id":"E32","title":"Frequency Map String","question":"Return frequency map of characters in a string.","constraints":"ASCII","examples":[{"input":"\"aa\"","output":"{'a':2}"}]},
    {"id":"E33","title":"Two Sum (Basic)","question":"Find two indices such that numbers add to target (brute force allowed).","constraints":"Return any pair or -1","examples":[{"input":"[2,7,11,15],target=9","output":"[0,1]"}]},
    {"id":"E34","title":"Intersection Of Arrays","question":"Return intersection of two arrays (unique elements).","constraints":"Integers","examples":[{"input":"[1,2],[2,2]","output":"[2]"}]},
    {"id":"E35","title":"Contains Duplicates","question":"Return true if array contains duplicates.","constraints":"Integers","examples":[{"input":"[1,2,1]","output":"true"}]},
    {"id":"E36","title":"Max Frequency Element","question":"Return element with maximum frequency in array.","constraints":"Return any if tie","examples":[{"input":"[1,2,2,3]","output":"2"}]},
    {"id":"E37","title":"Anagram Using Map","question":"Check if two strings are anagrams using a map.","constraints":"Lowercase","examples":[{"input":"\"anagram\",\"nagaram\"","output":"true"}]},
    {"id":"E38","title":"Group Identical","question":"Group identical elements together (simple bucketing).","constraints":"Return groups","examples":[{"input":"[1,1,2]","output":"[[1,1],[2]]"}]},
    {"id":"E39","title":"Pair Sum Sorted","question":"Given sorted array, return whether a pair sums to target (two pointers).","constraints":"Sorted array","examples":[{"input":"[1,2,3],target=5","output":"true"}]},
    {"id":"E40","title":"Remove Dups From Sorted String","question":"Remove duplicates from sorted string in-place.","constraints":"Return new length","examples":[{"input":"\"aabb\"","output":"\"ab\""}]},
    {"id":"E41","title":"Move Negatives One Side","question":"Move negative numbers to the left side preserving relative order.","constraints":"Stable partition","examples":[{"input":"[1,-1,2,-2]","output":"[-1,-2,1,2]"}]},
    {"id":"E42","title":"Pair Closest To Target (Easy)","question":"Find pair sum closest to target (small n).","constraints":"Return one pair","examples":[{"input":"[1,3,4],target=6","output":"[3,4]"}]},
    {"id":"E43","title":"Compare Strings Ignore Case Spaces","question":"Check if two strings are equal ignoring case and spaces.","constraints":"Normalize first","examples":[{"input":"\"Hi You\",\"hiyou\"","output":"true"}]},
    {"id":"E44","title":"Is Prime","question":"Check if a number is prime (simple test).","constraints":"n >= 0","examples":[{"input":"7","output":"true"}]},
    {"id":"E45","title":"Iterative Factorial","question":"Return factorial of n using iteration.","constraints":"n small (e.g., <= 20)","examples":[{"input":"5","output":"120"}]},
    {"id":"E46","title":"Iterative Fibonacci","question":"Return n-th Fibonacci number iteratively.","constraints":"n small","examples":[{"input":"5","output":"5"}]},
    {"id":"E47","title":"Count Digits","question":"Return number of digits in integer.","constraints":"n >= 0","examples":[{"input":"12345","output":"5"}]},
    {"id":"E48","title":"Reverse Digits","question":"Reverse digits of an integer, preserving sign.","constraints":"Handle overflow not required","examples":[{"input":"123","output":"321"}]},
    {"id":"E49","title":"Sum Of Digits","question":"Return sum of digits of a number.","constraints":"Non-negative","examples":[{"input":"123","output":"6"}]},
    {"id":"E50","title":"Perfect Square Check","question":"Check if integer is a perfect square.","constraints":"Non-negative","examples":[{"input":"16","output":"true"}]}
  ],
  "medium": [
    {"id":"M1","title":"3Sum","question":"Find all unique triplets in array that sum to zero.","constraints":"Return unique triplets","examples":[{"input":"[-1,0,1,2,-1,-4]","output":"[[-1,-1,2],[-1,0,1]]"}]},
    {"id":"M2","title":"Sort Colors","question":"Sort array containing 0,1,2 (Dutch National Flag).","constraints":"In-place","examples":[{"input":"[2,0,2,1,1,0]","output":"[0,0,1,1,2,2]"}]},
    {"id":"M3","title":"Longest Consecutive Sequence","question":"Find length of longest consecutive elements sequence.","constraints":"O(n) expected","examples":[{"input":"[100,4,200,1,3,2]","output":"4"}]},
    {"id":"M4","title":"Subarray Sum Equals K","question":"Find number of continuous subarrays that sum to k.","constraints":"Integers can be negative","examples":[{"input":"[1,1,1],k=2","output":"2"}]},
    {"id":"M5","title":"Pairs With Given Difference","question":"Find all pairs with difference equal to k.","constraints":"Return pairs","examples":[{"input":"[1,5,3],k=2","output":"[(1,3)]"}]},
    {"id":"M6","title":"Container With Most Water","question":"Given heights, find max area of water container.","constraints":"Indices as width","examples":[{"input":"[1,8,6,2,5,4,8,3,7]","output":"49"}]},
    {"id":"M7","title":"Product Except Self","question":"Return array where result[i] is product of all elements except nums[i] without using division.","constraints":"O(n) time","examples":[{"input":"[1,2,3,4]","output":"[24,12,8,6]"}]},
    {"id":"M8","title":"Find Peak Element","question":"Find a peak element index (element > neighbors).","constraints":"Any peak OK","examples":[{"input":"[1,2,3,1]","output":"2"}]},
    {"id":"M9","title":"Insert Interval","question":"Insert and merge intervals.","constraints":"Intervals list sorted by start","examples":[{"input":"[[1,3],[6,9]], insert [2,5]","output":"[[1,5],[6,9]]"}]},
    {"id":"M10","title":"Merge Intervals","question":"Merge overlapping intervals.","constraints":"Return merged list","examples":[{"input":"[[1,4],[4,5]]","output":"[[1,5]]"}]},
    {"id":"M11","title":"Longest Substring No Repeat","question":"Return length of longest substring without repeating characters.","constraints":"Use sliding window","examples":[{"input":"\"abcabcbb\"","output":"3"}]},
    {"id":"M12","title":"At Most K Distinct","question":"Longest substring with at most K distinct characters.","constraints":"k >= 1","examples":[{"input":"s=\"eceba\",k=2","output":"3"}]},
    {"id":"M13","title":"Minimum Window Substring","question":"Find minimum window substring containing all characters of target.","constraints":"Return empty if none","examples":[{"input":"s=\"ADOBECODEBANC\",t=\"ABC\"","output":"\"BANC\""}]},
    {"id":"M14","title":"Longest Repeating Char Replacement","question":"Find length after replacing at most k chars to get longest repeating char substring.","constraints":"k >= 0","examples":[{"input":"\"AABABBA\",k=1","output":"4"}]},
    {"id":"M15","title":"Smallest Subarray Sum >= Target","question":"Return length of smallest subarray with sum >= target.","constraints":"Positive ints","examples":[{"input":"[2,3,1,2,4,3],target=7","output":"2"}]},
    {"id":"M16","title":"Subarrays Product Less Than K","question":"Count subarrays where product < k.","constraints":"k > 0","examples":[{"input":"[10,5,2,6],k=100","output":"8"}]},
    {"id":"M17","title":"Max Average Subarray","question":"Find contiguous subarray of length k with max average.","constraints":"k <= n","examples":[{"input":"[1,12,-5,-6,50,3],k=4","output":"12.75"}]},
    {"id":"M18","title":"Count Anagram Occurrences","question":"Count anagram occurrences of p in s.","constraints":"Return count","examples":[{"input":"s=\"cbaebabacd\",p=\"abc\"","output":"2"}]},
    {"id":"M19","title":"Longest Vowel Substring","question":"Longest substring containing only vowels.","constraints":"Simple vowels","examples":[{"input":"\"earthproblem\"","output":"2"}]},
    {"id":"M20","title":"Equal 0s and 1s","question":"Longest substring with equal number of 0s and 1s.","constraints":"Binary string","examples":[{"input":"\"0101\"","output":"4"}]},
    {"id":"M21","title":"Group Anagrams","question":"Group anagram strings together.","constraints":"Return list of groups","examples":[{"input":"[\"eat\",\"tea\",\"tan\",\"ate\",\"nat\",\"bat\"]","output":"[[eat,tea,ate],[tan,nat],[bat]]"}]},
    {"id":"M22","title":"Top K Frequent Elements","question":"Return k most frequent elements.","constraints":"k valid","examples":[{"input":"[1,1,1,2,2,3],k=2","output":"[1,2]"}]},
    {"id":"M23","title":"Sort Characters By Frequency","question":"Return string sorted by char frequency.","constraints":"ASCII letters","examples":[{"input":"\"tree\"","output":"\"eert\""}]},
    {"id":"M24","title":"Duplicate Files","question":"Find duplicate file paths by content.","constraints":"Return groups of paths","examples":[{"input":"[list of paths]","output":"[[paths with same content]]"}]},
    {"id":"M25","title":"Longest Harmonious Subseq","question":"Find longest subsequence where max-min=1","constraints":"Return length","examples":[{"input":"[1,3,2,2,5,2,3,7]","output":"5"}]},
    {"id":"M26","title":"Search In Rotated Sorted Array","question":"Search target in rotated sorted array and return index or -1.","constraints":"No duplicates","examples":[{"input":"[4,5,6,7,0,1,2],target=0","output":"4"}]},
    {"id":"M27","title":"Find Min In Rotated Array","question":"Find minimum element in rotated sorted array.","constraints":"No duplicates","examples":[{"input":"[3,4,5,1,2]","output":"1"}]},
    {"id":"M28","title":"Single Non-duplicate Binary Search","question":"Find single non-duplicate element where others appear twice using binary search.","constraints":"Sorted array","examples":[{"input":"[1,1,2,3,3]","output":"2"}]},
    {"id":"M29","title":"Kth Smallest In Sorted Matrix","question":"Find kth smallest element in sorted matrix.","constraints":"Each row and column sorted","examples":[{"input":"matrix=[[1,5,9],[2,6,10],[3,7,11]],k=5","output":"6"}]},
    {"id":"M30","title":"First And Last Position","question":"Find first and last position of target in sorted array.","constraints":"Return [-1,-1] if not found","examples":[{"input":"[5,7,7,8,8,10],target=8","output":"[3,4]"}]},
    {"id":"M31","title":"Climbing Stairs Variable Jumps","question":"Number of ways to reach top given variable jumps.","constraints":"DP expected","examples":[{"input":"n=3,jumps=[1,2]","output":"3"}]},
    {"id":"M32","title":"House Robber","question":"Max money without robbing adjacent houses.","constraints":"Non-negative ints","examples":[{"input":"[1,2,3,1]","output":"4"}]},
    {"id":"M33","title":"Coin Change (fewest coins)","question":"Return fewest coins to make amount or -1.","constraints":"Infinite coin supply","examples":[{"input":"coins=[1,2,5],amount=11","output":"3"}]},
    {"id":"M34","title":"Longest Increasing Subsequence","question":"Length of LIS in array.","constraints":"n up to moderate","examples":[{"input":"[10,9,2,5,3,7,101,18]","output":"4"}]},
    {"id":"M35","title":"Max Subarray With One Deletion","question":"Max sum subarray where you can delete at most one element.","constraints":"Return max sum","examples":[{"input":"[1,-2,0,3]","output":"4"}]},
    {"id":"M36","title":"Decode Ways","question":"Number of ways to decode numeric string to letters.","constraints":"Leading zeros invalid","examples":[{"input":"\"12\"","output":"2"}]},
    {"id":"M37","title":"Unique Paths II","question":"Unique paths in grid with obstacles.","constraints":"Grid with 0/1 for free/obstacle","examples":[{"input":"[[0,0,0],[0,1,0],[0,0,0]]","output":"2"}]},
    {"id":"M38","title":"Palindromic Subseq Length","question":"Return length of longest palindromic subsequence.","constraints":"DP expected","examples":[{"input":"\"bbab\"","output":"3"}]},
    {"id":"M39","title":"Target Sum Ways","question":"Count ways to assign + and - to get target sum.","constraints":"Small n","examples":[{"input":"nums=[1,1,1,1,1],target=3","output":"5"}]},
    {"id":"M40","title":"Partition Equal Subset Sum","question":"Check if array can be partitioned into equal sum subsets.","constraints":"Integers non-negative","examples":[{"input":"[1,5,11,5]","output":"true"}]},
    {"id":"M41","title":"Generate Subsets","question":"Return all subsets of array.","constraints":"No duplicates expected","examples":[{"input":"[1,2]","output":"[[],[1],[2],[1,2]]"}]},
    {"id":"M42","title":"Generate Permutations","question":"Return all permutations of array.","constraints":"Distinct elements","examples":[{"input":"[1,2]","output":"[[1,2],[2,1]]"}]},
    {"id":"M43","title":"Combination Sum","question":"Return combinations that sum to target using unlimited candidates.","constraints":"No duplicate combinations","examples":[{"input":"candidates=[2,3,6,7],target=7","output":"[[7],[2,2,3]]"}]},
    {"id":"M44","title":"Phone Letter Combinations","question":"Return all letter combinations of a phone number digit string.","constraints":"Digits 2-9","examples":[{"input":"\"23\"","output":"[\"ad\",\"ae\",\"af\",\"bd\",\"be\",\"bf\",\"cd\",\"ce\",\"cf\"]"}]},
    {"id":"M45","title":"Letter Case Permutation","question":"Return all strings by toggling case of letters.","constraints":"Return unique","examples":[{"input":"\"a1b2\"","output":"[\"a1b2\",\"A1b2\",\"a1B2\",\"A1B2\"]"}]},
    {"id":"M46","title":"Binary Tree Level Order","question":"Return level-order traversal of binary tree nodes.","constraints":"Standard tree rules","examples":[{"input":"[3,9,20,null,null,15,7]","output":"[[3],[9,20],[15,7]]"}]},
    {"id":"M47","title":"Lowest Common Ancestor (Binary Tree)","question":"Find LCA of two nodes in binary tree.","constraints":"Nodes guaranteed present","examples":[{"input":"tree, p=5,q=1","output":"3"}]},
    {"id":"M48","title":"Identical Trees","question":"Check if two binary trees are identical.","constraints":"Return boolean","examples":[{"input":"[1,2,3] and [1,2,3]","output":"true"}]},
    {"id":"M49","title":"Sorted Array To BST","question":"Convert sorted array to height-balanced BST.","constraints":"Use middle as root","examples":[{"input":"[-10,-3,0,5,9]","output":"[0,-3,9,-10,null,5]"}]},
    {"id":"M50","title":"Diameter Of Binary Tree","question":"Return diameter (number of nodes on longest path).","constraints":"Standard tree","examples":[{"input":"[1,2,3,4,5]","output":"3"}]}
  ],
  "hard": [
    {"id":"H1","title":"Longest Valid Parentheses","question":"Find length of longest valid parentheses substring.","constraints":"O(n) or DP","examples":[{"input":"\")(()())\"","output":"4"}]},
    {"id":"H2","title":"Edit Distance","question":"Compute minimum operations to convert word1 to word2 (insert, delete, replace).","constraints":"DP expected","examples":[{"input":"\"horse\",\"ros\"","output":"3"}]},
    {"id":"H3","title":"Burst Balloons","question":"Max coins by bursting balloons with DP interval optimization.","constraints":"n up to moderate","examples":[{"input":"[3,1,5,8]","output":"167"}]},
    {"id":"H4","title":"Word Break II","question":"Return all possible sentences formed by word break.","constraints":"Backtracking+memo","examples":[{"input":"s=\"catsanddog\",wordDict=[\"cat\",\"cats\",\"and\",\"sand\",\"dog\"]","output":"[\"cats and dog\",\"cat sand dog\"]"}]},
    {"id":"H5","title":"Max Profit K Transactions","question":"Max profit with at most k stock transactions.","constraints":"DP optimization","examples":[{"input":"k=2,prices=[2,4,1]","output":"2"}]},
    {"id":"H6","title":"Regular Expression Matching","question":"Implement regex matching with '.' and '*'.","constraints":"DP expected","examples":[{"input":"s=\"aa\",p=\"a*\"","output":"true"}]},
    {"id":"H7","title":"Wildcard Matching","question":"Implement wildcard matching with ? and *.","constraints":"DP expected","examples":[{"input":"s=\"aa\",p=\"*\"","output":"true"}]},
    {"id":"H8","title":"Minimum Window Subsequence","question":"Find shortest subsequence in s that contains t in order.","constraints":"Hard DP","examples":[{"input":"s=\"abcdebdde\",t=\"bde\"","output":"\"bcde\""}]},
    {"id":"H9","title":"Palindrome Partitioning II","question":"Min cuts needed for palindrome partitioning of string.","constraints":"DP","examples":[{"input":"\"aab\"","output":"1"}]},
    {"id":"H10","title":"Count Palindromic Substrings","question":"Count palindromic substrings in a string (optimized DP).","constraints":"O(n^2)","examples":[{"input":"\"aaa\"","output":"6"}]},
    {"id":"H11","title":"N-Queens","question":"Return all distinct N-Queens solutions.","constraints":"Backtracking","examples":[{"input":"4","output":"[[\".Q..\",\"...Q\",\"Q...\",\"..Q.\"],[\".Q..\",\"Q...\",\"...Q\",\".Q..\"]]"}]},
    {"id":"H12","title":"Sudoku Solver","question":"Fill a 9x9 Sudoku board.","constraints":"Backtracking","examples":[{"input":"partially filled board","output":"filled board"}]},
    {"id":"H13","title":"Word Search II","question":"Find all words from list in board using trie+backtracking.","constraints":"Large dict","examples":[{"input":"board and words list","output":"found words"}]},
    {"id":"H14","title":"Expression Add Operators","question":"Add operators to form target value from digits string.","constraints":"Backtracking","examples":[{"input":"\"123\",6","output":"[\"1+2+3\",\"1*2*3\"]"}]},
    {"id":"H15","title":"Restore IP Addresses","question":"Return all possible valid IP addresses from string.","constraints":"Backtracking","examples":[{"input":"\"25525511135\"","output":"[\"255.255.11.135\",\"255.255.111.35\"]"}]},
    {"id":"H16","title":"Course Schedule II","question":"Return order to finish courses given prerequisites (topo sort).","constraints":"Detect cycles","examples":[{"input":"2,[[1,0]]","output":"[0,1]"}]},
    {"id":"H17","title":"Alien Dictionary","question":"Given sorted words in alien language, deduce character order using graph/topo sort.","constraints":"Detect invalid orders","examples":[{"input":"[\"wrt\",\"wrf\",\"er\",\"ett\",\"rftt\"]","output":"\"wertf\""}]},
    {"id":"H18","title":"Minimum Height Trees","question":"Find all roots resulting in min height trees.","constraints":"Graph pruning BFS","examples":[{"input":"n=4,edges=[[1,0],[1,2],[1,3]]","output":"[1]"}]},
    {"id":"H19","title":"Number Of Islands II","question":"Add lands one by one and return number of islands after each add (union-find).","constraints":"Union-Find","examples":[{"input":"m,n and positions","output":"counts array"}]},
    {"id":"H20","title":"Dijkstra Shortest Path","question":"Return shortest path distances from source in weighted graph.","constraints":"Use priority queue","examples":[{"input":"graph,source","output":"distances"}]},
    {"id":"H21","title":"Candy Distribution","question":"Distribute candies such that higher rating gets more than neighbors minimal candies count.","constraints":"Greedy two-pass","examples":[{"input":"[1,0,2]","output":"5"}]},
    {"id":"H22","title":"Gas Station","question":"Return start index if can complete circuit, else -1.","constraints":"Greedy O(n)","examples":[{"input":"gas=[1,2,3],cost=[2,2,2]","output":"-1"}]},
    {"id":"H23","title":"Jump Game II","question":"Min jumps to reach end.","constraints":"Greedy O(n)","examples":[{"input":"[2,3,1,1,4]","output":"2"}]},
    {"id":"H24","title":"Min Arrows Burst Balloons","question":"Min number of arrows to burst all balloons (intervals).","constraints":"Greedy","examples":[{"input":"[[10,16],[2,8],[1,6],[7,12]]","output":"2"}]},
    {"id":"H25","title":"Merge Stones Hard","question":"Merge stones with cost rules to minimize cost (DP/greedy hybrid).","constraints":"Complex DP","examples":[{"input":"[3,2,4,1],k=2","output":"20"}]},
    {"id":"H26","title":"Median Of Data Stream","question":"Design structure to find median in data stream.","constraints":"Heaps","examples":[{"input":"add 1, add 2, findMedian","output":"1.5"}]},
    {"id":"H27","title":"Sliding Window Maximum Hard","question":"Return max in each window of size k efficiently (deque).","constraints":"O(n)","examples":[{"input":"[1,3,-1,-3,5,3,6,7],k=3","output":"[3,3,5,5,6,7]"}]},
    {"id":"H28","title":"Kth Largest In Stream","question":"Design structure to return kth largest in stream.","constraints":"Heap maintenance","examples":[{"input":"k=3,stream", "output":"values"}]},
    {"id":"H29","title":"Reorganize String","question":"Rearrange string so no adjacent same characters or return \"\".","constraints":"Greedy heap","examples":[{"input":"\"aab\"","output":"\"aba\""}]},
    {"id":"H30","title":"K Smallest Pairs","question":"Return k pairs with smallest sums from two arrays.","constraints":"Use heap","examples":[{"input":"[1,7,11],[2,4,6],k=3","output":"[[1,2],[1,4],[1,6]]"}]},
    {"id":"H31","title":"Trapping Rain Water II","question":"Trap rain water in 2D height map using PQ.","constraints":"Hard BFS+heap","examples":[{"input":"matrix","output":"trapped volume"}]},
    {"id":"H32","title":"Maximal Rectangle","question":"Max rectangle of 1s in binary matrix.","constraints":"Histogram trick","examples":[{"input":"matrix","output":"area"}]},
    {"id":"H33","title":"Segment Tree Range Sum","question":"Support range sum queries and point updates with segment tree.","constraints":"Build/update/query","examples":[{"input":"operations","output":"results"}]},
    {"id":"H34","title":"Fenwick Tree Problems","question":"Implement BIT for prefix sums and updates.","constraints":"Indexing caution","examples":[{"input":"ops","output":"results"}]},
    {"id":"H35","title":"Design LFU Cache","question":"Design Least Frequently Used cache with O(1) operations.","constraints":"Data structure design","examples":[{"input":"ops","output":"values"}]},
    {"id":"H36","title":"Kth Smallest In Multiplication Table","question":"Find k-th smallest number in m x n multiplication table.","constraints":"Binary search on answer","examples":[{"input":"m=3,n=3,k=5","output":"3"}]},
    {"id":"H37","title":"Split Array Largest Sum","question":"Split array into m subarrays to minimize largest sum (binary search on answer).","constraints":"Return min largest sum","examples":[{"input":"[7,2,5,10,8],m=2","output":"18"}]},
    {"id":"H38","title":"Ship Packages Within D Days","question":"Capacity to ship packages within D days minimal capacity.","constraints":"Binary search on answer","examples":[{"input":"[1,2,3,4,5,6,7,8,9],D=5","output":"15"}]},
    {"id":"H39","title":"Min Max Distance To Gas Stations","question":"Minimize maximum distance to gas stations placing additional ones.","constraints":"Binary search on continuous answer","examples":[{"input":"positions, k","output":"distance"}]},
    {"id":"H40","title":"Kth Smallest Pair Distance","question":"Find k-th smallest absolute difference between pairs.","constraints":"Binary search on answer","examples":[{"input":"[1,3,1],k=1","output":"0"}]},
    {"id":"H41","title":"Serialize Deserialize Binary Tree","question":"Serialize and deserialize binary tree to/from string.","constraints":"Any traversal with markers","examples":[{"input":"tree","output":"string"}]},
    {"id":"H42","title":"Word Dictionary With Wildcard","question":"Design add/search data structure with '.' wildcard using Trie.","constraints":"Fast search","examples":[{"input":"add \"bad\", search \"b.d\"","output":"true"}]},
    {"id":"H43","title":"LCA BST Advanced","question":"Lowest common ancestor in BST with modifications (hard variants).","constraints":"Handle duplicates or special structure","examples":[{"input":"tree","output":"node"}]},
    {"id":"H44","title":"Largest BST Subtree","question":"Find size of largest BST subtree in binary tree.","constraints":"DFS with ranges","examples":[{"input":"tree","output":"size"}]},
    {"id":"H45","title":"Binary Tree Max Path Sum","question":"Max path sum (can start and end anywhere).","constraints":"Return max sum","examples":[{"input":"[-10,9,20,null,null,15,7]","output":"42"}]},
    {"id":"H46","title":"Critical Connections (Tarjan)","question":"Find bridges in undirected graph using Tarjan's algorithm.","constraints":"Return list of edges","examples":[{"input":"n,edges","output":"bridges"}]},
    {"id":"H47","title":"Detect Directed Cycle DFS","question":"Detect and return directed cycle in graph (hard constraints).","constraints":"Return cycle nodes","examples":[{"input":"graph","output":"cycle"}]},
    {"id":"H48","title":"Bipartite Check Hard","question":"Check if graph can be bipartite under extra constraints.","constraints":"Large graph","examples":[{"input":"graph","output":"true/false"}]},
    {"id":"H49","title":"Redundant Connection II","question":"Find edge to remove to form a rooted tree when one extra edge added.","constraints":"Graph union-find + indegree","examples":[{"input":"edges","output":"edge"}]},
    {"id":"H50","title":"Constrained MST","question":"Find MST with extra constraints (e.g., must include particular edges)","constraints":"Kruskal variations","examples":[{"input":"graph,constraints","output":"mst cost"}]}
  ]
}